Compare_SQL_RedShift.py
DaskUtil.py
MasterClass.py
CompareSqlRedshiftFramework-0.0.1.dist-info/LICENSE.txt
CompareSqlRedshiftFramework-0.0.1.dist-info/METADATA
CompareSqlRedshiftFramework-0.0.1.dist-info/WHEEL
CompareSqlRedshiftFramework-0.0.1.dist-info/top_level.txt
CompareSqlRedshiftFramework-0.0.1.dist-info/RECORD
